{
	"re_xml":
	{
		"system_grids":
		[
			{
				"name":"admin",
				"display_name":"Admin",
				"head_color":"#43196b",
				"back_color":"#652b8d",
				"status": "active",
				"last_updated":1,
				"grid_order":21,
				"elements": "[{\"name\":\"form46\",\"onclick\":\"form46_header_ini(); form46_ini();\",\"display_name\":\"Set Defaults\",\"type\":\"forms\"},{\"name\":\"form50\",\"onclick\":\"form50_header_ini(); form50_ini();\",\"display_name\":\"Set System Values\",\"type\":\"forms\"},{\"name\":\"form80\",\"onclick\":\"form80_header_ini();\",\"display_name\":\"De-duplication mapping\",\"type\":\"forms\"},{\"name\":\"form95\",\"onclick\":\"form95_header_ini(); form95_ini();\",\"display_name\":\"Data Import\",\"type\":\"forms\"},{\"name\":\"form100\",\"onclick\":\"form100_header_ini(); form100_ini();\",\"display_name\":\"Sync\",\"type\":\"forms\"},{\"name\":\"form257\",\"onclick\":\"form257_header_ini(); form257_ini();\",\"display_name\":\"User Accounts\",\"type\":\"forms\"},{\"name\":\"form51\",\"onclick\":\"form51_header_ini();\",\"display_name\":\"Access control\",\"type\":\"forms\"},{\"name\":\"form149\",\"onclick\":\"form149_header_ini(); form149_ini();\",\"display_name\":\"Assign Roles\",\"type\":\"forms\"},{\"name\":\"form105\",\"onclick\":\"form105_header_ini(); form105_ini();\",\"display_name\":\"Data Access\",\"type\":\"forms\"},{\"name\":\"form110\",\"onclick\":\"form110_header_ini(); form110_ini();\",\"display_name\":\"Manage Reports\",\"type\":\"forms\"},{\"name\":\"form111\",\"onclick\":\"form111_header_ini(); form111_ini();\",\"display_name\":\"Create Reports\",\"type\":\"forms\"},{\"name\":\"form123\",\"onclick\":\"form123_header_ini(); form123_ini();\",\"display_name\":\"Mandatory Attributes\",\"type\":\"forms\"},{\"name\":\"form177\",\"onclick\":\"form177_header_ini(); form177_ini();\",\"display_name\":\"Prioritization Parameters\",\"type\":\"forms\"},{\"name\":\"form195\",\"onclick\":\"form195_header_ini(); form195_ini();\",\"display_name\":\"Letterhead\",\"type\":\"forms\"},{\"name\":\"form286\",\"onclick\":\"form286_header_ini(); form286_ini();\",\"display_name\":\"Billing\",\"type\":\"forms\"},{\"name\":\"form290\",\"onclick\":\"form290_header_ini(); form290_ini();\",\"display_name\":\"Cities\",\"type\":\"forms\"}]"	
			},
			{
				"name":"system_config",
				"display_name":"System",
				"head_color":"#C4A240",
				"back_color":"#E6C462",
				"status": "active",
				"last_updated":1,
				"grid_order":22,
				"elements": "[{\"name\":\"form314\",\"onclick\":\"form314_header_ini(); form314_ini();\",\"display_name\":\"Object Pages\",\"type\":\"forms\"},{\"name\":\"form48\",\"onclick\":\"form48_header_ini(); form48_ini();\",\"display_name\":\"Select Reports\",\"type\":\"forms\"},{\"name\":\"form49\",\"onclick\":\"form49_header_ini(); form49_ini();\",\"display_name\":\"Select Forms\",\"type\":\"forms\"},{\"name\":\"form147\",\"onclick\":\"form147_header_ini(); form147_ini();\",\"display_name\":\"Create Roles\",\"type\":\"forms\"},{\"name\":\"form148\",\"onclick\":\"form148_header_ini(); form148_ini();\",\"display_name\":\"Manage Roles\",\"type\":\"forms\"},{\"name\":\"form142\",\"onclick\":\"form142_header_ini(); form142_ini();\",\"display_name\":\"Create Questionnaires\",\"type\":\"forms\"},{\"name\":\"form143\",\"onclick\":\"form143_header_ini(); form143_ini();\",\"display_name\":\"Manage Questionnaires\",\"type\":\"forms\"},{\"name\":\"form191\",\"onclick\":\"form191_header_ini(); form191_ini();\",\"display_name\":\"Values Lists\",\"type\":\"forms\"},{\"name\":\"form262\",\"onclick\":\"form262_header_ini(); form262_ini();\",\"display_name\":\"Manage Grids\",\"type\":\"forms\"},{\"name\":\"form263\",\"onclick\":\"form263_header_ini(); form263_ini();\",\"display_name\":\"Arrange Grid Tabs\",\"type\":\"forms\"},{\"name\":\"form264\",\"onclick\":\"form264_header_ini(); form264_ini();\",\"display_name\":\"Grid Metrics\",\"type\":\"forms\"},{\"name\":\"form276\",\"onclick\":\"form276_header_ini(); form276_ini();\",\"display_name\":\"Search Queries\",\"type\":\"forms\"},{\"name\":\"form277\",\"onclick\":\"form277_header_ini(); form277_ini();\",\"display_name\":\"Notifications\",\"type\":\"forms\"},{\"name\":\"form278\",\"onclick\":\"form278_header_ini(); form278_ini();\",\"display_name\":\"Values List\",\"type\":\"forms\"},{\"name\":\"form281\",\"onclick\":\"form281_header_ini(); form281_ini();\",\"display_name\":\"Pop-boxes\",\"type\":\"forms\"},{\"name\":\"form287\",\"onclick\":\"form287_header_ini(); form287_ini();\",\"display_name\":\"Table Structure\",\"type\":\"forms\"},{\"name\":\"form288\",\"onclick\":\"form288_header_ini(); form288_ini();\",\"display_name\":\"User Form Definition\",\"type\":\"forms\"}]"
			}				
		]
	}
}